{
	"class" : {
		 },
	"instance" : {
		"addAssignmentEditor" : "fabiandumke 6/16/2014 18:25",
		"addPrivilegedTutorSelector" : "fabiandumke 6/16/2014 18:32",
		"addTopicPoolEditor" : "fabiandumke 6/16/2014 18:34",
		"addTutorSelector" : "fabiandumke 6/16/2014 18:34",
		"assignmentEditors" : "fm 6/20/2013 13:53",
		"assignmentEditors:" : "fm 6/20/2013 13:53",
		"course" : "fm 7/15/2013 15:51",
		"course:" : "fm 7/16/2013 15:31",
		"distributeAssignmentEditorIDs" : "fm 7/16/2013 11:41",
		"initializeRadioButtonTexts" : "fm 7/16/2013 11:36",
		"initializeWithCourse" : "JB 6/19/2014 09:57",
		"privilegedTutorComponent" : "JB 6/19/2014 09:51",
		"privilegedTutorComponent:" : "JB 6/19/2014 09:51",
		"privilegedTutorSelectors" : "JB 6/7/2014 15:45",
		"privilegedTutorSelectors:" : "JB 6/7/2014 15:45",
		"renderAssignmentEditorsContainerOn:" : "fm 7/16/2013 15:56",
		"renderAssignmentEditorsOn:" : "fm 6/20/2013 20:33",
		"renderContentOn:" : "fm 7/16/2013 15:56",
		"renderCourseInfoEditorOn:" : "JB 6/7/2014 15:46",
		"renderDeleteCourseButtonOn:" : "fm 7/16/2013 17:22",
		"renderDeleteCourseSeriouslyButtonOn:" : "fm 7/16/2013 17:22",
		"renderGroupDeadlineInputOn:" : "MalteMues 7/10/2013 23:29",
		"renderGroupEditorOn:" : "fm 7/8/2013 09:54",
		"renderGroupSizeInputOn:" : "fm 7/3/2013 16:59",
		"renderGroupsAndTopicsEditorOn:" : "fm 7/16/2013 15:48",
		"renderHeadingOn:" : "fm 7/16/2013 11:43",
		"renderMailinglistEditorOn:" : "fm 6/27/2013 18:45",
		"renderPrivilegedTutorSelectorsContainerOn:" : "JB 6/21/2014 11:50",
		"renderPublishedEditorOn:" : "fm 6/27/2013 18:45",
		"renderSemesterEditorOn:" : "fm 6/27/2013 18:45",
		"renderTitleEditorOn:" : "fm 6/28/2013 00:23",
		"renderTopicPoolEditorContainerOn:" : "fm 7/16/2013 15:54",
		"renderTopicPoolEditorsOn:" : "fm 7/16/2013 15:53",
		"renderTopicTypeEditorOn:" : "fm 7/16/2013 15:41",
		"renderTutorSelectorsContainerOn:" : "fm 7/16/2013 11:45",
		"renderTutorSelectorsOn:" : "fm 6/20/2013 14:14",
		"renderWebsiteEditorOn:" : "fm 6/27/2013 18:45",
		"resetAssignmentEditors" : "fabiandumke 6/16/2014 18:13",
		"resetPrivilegedTutorSelectors" : "JB 6/19/2014 09:52",
		"resetTopicPoolEditors" : "fm 7/16/2013 15:44",
		"resetTutorSelectors" : "fm 7/16/2013 11:39",
		"seasonText" : "fm 5/25/2013 13:23:34.235",
		"seasonText:" : "fm 5/25/2013 13:23:27.605",
		"topicPoolEditors" : "fm 7/16/2013 15:45",
		"topicPoolEditors:" : "fm 7/16/2013 15:45",
		"topicTypeText" : "jw 6/20/2013 23:11",
		"topicTypeText:" : "jw 6/20/2013 23:11",
		"tutorSelectors" : "fm 5/24/2013 17:52:54.569",
		"tutorSelectors:" : "fm 5/24/2013 17:52:46.447",
		"validateTopicTypeEditor:" : "fm 7/16/2013 11:39",
		"validateWebsiteChange:" : "fm 6/6/2013 14:10:42.518" } }
